SyncFolder/__init__.py
SyncFolder/processor.py
SyncFolder-0.1.3.dist-info/LICENSE
SyncFolder-0.1.3.dist-info/METADATA
SyncFolder-0.1.3.dist-info/WHEEL
SyncFolder-0.1.3.dist-info/entry_points.txt
SyncFolder-0.1.3.dist-info/top_level.txt
SyncFolder-0.1.3.dist-info/RECORD
