Metadata-Version: 2.1
Name: SyncFolder
Version: 0.1.3
Summary: Python package for synchronizing folders.
Home-page: https://github.com/songs18/SyncFolder
Author: songs18
Author-email: songhaohao2018@cqu.edu.cn
License: MIT
Platform: all
Requires-Python: >=3.3
License-File: LICENSE
